CHANGES.txt
DEPENDENCES.txt
README.txt
setup.py
src/ng/__init__.py
src/ng.index.area.egg-info/PKG-INFO
src/ng.index.area.egg-info/SOURCES.txt
src/ng.index.area.egg-info/dependency_links.txt
src/ng.index.area.egg-info/namespace_packages.txt
src/ng.index.area.egg-info/not-zip-safe
src/ng.index.area.egg-info/requires.txt
src/ng.index.area.egg-info/top_level.txt
src/ng/index/__init__.py
src/ng/index/area/__init__.py
src/ng/index/area/areabase.py
src/ng/index/area/areaindex.py
src/ng/index/area/configure.zcml
src/ng/index/area/geoellipsoidprojection.py
src/ng/index/area/interfaces.py
src/ng/index/area/ng.index.area.proposal.txt
src/ng/index/area/ng.index.area.txt
src/ng/index/area/browser/__init__.py
src/ng/index/area/browser/configure.zcml
src/ng/index/area/etc/ng.index.area-configure.zcml